Metadata-Version: 2.1
Name: miguelemosreverte
Version: 0.0.18
Summary: A small little package
Home-page: https://github.com/pypa/sampleproject
Author: miguelemosreverte
Author-email: miguelemosreverte@gmail.com
License: UNKNOWN
Platform: UNKNOWN
Classifier: Programming Language :: Python :: 3
Classifier: License :: OSI Approved :: MIT License
Classifier: Operating System :: OS Independent
